{
  "as_of_utc": "2025-01-30T00:00:00Z",
  "season": 2025,
  "ratings": [
    {
      "team_id": "OKC",
      "team_abbr": "OKC",
      "rating": 6.652728915710886,
      "rank": 1
    },
    {
      "team_id": "CLE",
      "team_abbr": "CLE",
      "rating": 6.396589245807901,
      "rank": 2
    },
    {
      "team_id": "BOS",
      "team_abbr": "BOS",
      "rating": 5.515072670249767,
      "rank": 3
    },
    {
      "team_id": "DEN",
      "team_abbr": "DEN",
      "rating": 4.965651505644491,
      "rank": 4
    },
    {
      "team_id": "IND",
      "team_abbr": "IND",
      "rating": 4.518574089051291,
      "rank": 5
    },
    {
      "team_id": "MIN",
      "team_abbr": "MIN",
      "rating": 3.861248571250496,
      "rank": 6
    },
    {
      "team_id": "MIL",
      "team_abbr": "MIL",
      "rating": 3.8299176424562944,
      "rank": 7
    },
    {
      "team_id": "LAL",
      "team_abbr": "LAL",
      "rating": 3.532238125135091,
      "rank": 8
    },
    {
      "team_id": "LAC",
      "team_abbr": "LAC",
      "rating": 2.9401205462630093,
      "rank": 9
    },
    {
      "team_id": "NYK",
      "team_abbr": "NYK",
      "rating": 2.4091550269319466,
      "rank": 10
    },
    {
      "team_id": "MIA",
      "team_abbr": "MIA",
      "rating": 1.0913928143972176,
      "rank": 11
    },
    {
      "team_id": "HOU",
      "team_abbr": "HOU",
      "rating": 0.8289788539804412,
      "rank": 12
    },
    {
      "team_id": "GSW",
      "team_abbr": "GSW",
      "rating": 0.3920822582756612,
      "rank": 13
    },
    {
      "team_id": "ORL",
      "team_abbr": "ORL",
      "rating": 0.20048767616369828,
      "rank": 14
    },
    {
      "team_id": "DET",
      "team_abbr": "DET",
      "rating": -0.10030697149394441,
      "rank": 15
    },
    {
      "team_id": "CHI",
      "team_abbr": "CHI",
      "rating": -0.15897308363396734,
      "rank": 16
    },
    {
      "team_id": "ATL",
      "team_abbr": "ATL",
      "rating": -0.5433856721479711,
      "rank": 17
    },
    {
      "team_id": "SAC",
      "team_abbr": "SAC",
      "rating": -1.2523161771997082,
      "rank": 18
    },
    {
      "team_id": "MEM",
      "team_abbr": "MEM",
      "rating": -1.4155184903852063,
      "rank": 19
    },
    {
      "team_id": "POR",
      "team_abbr": "POR",
      "rating": -1.9162136628837492,
      "rank": 20
    },
    {
      "team_id": "SAS",
      "team_abbr": "SAS",
      "rating": -1.9812573562030122,
      "rank": 21
    },
    {
      "team_id": "PHX",
      "team_abbr": "PHX",
      "rating": -2.245592059384741,
      "rank": 22
    },
    {
      "team_id": "TOR",
      "team_abbr": "TOR",
      "rating": -2.279566813310402,
      "rank": 23
    },
    {
      "team_id": "DAL",
      "team_abbr": "DAL",
      "rating": -2.4417136988985013,
      "rank": 24
    },
    {
      "team_id": "BKN",
      "team_abbr": "BKN",
      "rating": -3.491832575164967,
      "rank": 25
    },
    {
      "team_id": "UTA",
      "team_abbr": "UTA",
      "rating": -4.406994252212711,
      "rank": 26
    },
    {
      "team_id": "PHI",
      "team_abbr": "PHI",
      "rating": -5.358236123356388,
      "rank": 27
    },
    {
      "team_id": "WAS",
      "team_abbr": "WAS",
      "rating": -6.189667730348194,
      "rank": 28
    },
    {
      "team_id": "CHA",
      "team_abbr": "CHA",
      "rating": -6.437774383129012,
      "rank": 29
    },
    {
      "team_id": "NOP",
      "team_abbr": "NOP",
      "rating": -7.040435523472205,
      "rank": 30
    }
  ]
}