{
  "as_of_utc": "2026-01-01T19:50:34Z",
  "tie_policy": "skip",
  "overall": {
    "games_total": 497,
    "win_rate_total": 0.682092555331992,
    "games_last_7": 51,
    "win_rate_last_7": 0.6470588235294118,
    "games_last_30": 189,
    "win_rate_last_30": 0.5978835978835979
  },
  "seasons": {
    "2026": {
      "games_total": 497,
      "win_rate_total": 0.682092555331992,
      "games_last_7": 51,
      "win_rate_last_7": 0.6470588235294118,
      "games_last_30": 189,
      "win_rate_last_30": 0.5978835978835979
    }
  }
}